{
  "phases": {
    "bytecode_size": 28,
    "metrics": [
      {
        "phase": "compile_to_ast",
        "elapsed": 0.242999475,
        "memory_usage": 1759748096
      },
      {
        "phase": "compile_ast_to_asm",
        "elapsed": 0.008818453,
        "memory_usage": 1760006144
      },
      {
        "phase": "generate_json_abi",
        "elapsed": 5.51e-07,
        "memory_usage": 1760006144
      },
      {
        "phase": "compile_asm_to_bytecode",
        "elapsed": 2.2592e-05,
        "memory_usage": 1760006144
      }
    ],
    "reused_modules": 0
  },
  "elapsed": "7.81",
  "cpu_usage": "100%",
  "memory": "702748KB",
  "build_type": "debug",
  "sway_apps_revision": "354bac23f11db6b2f89df53b46a8afe43c31911d",
  "sway_libs_revision": "c6ed898128cc516fab72d924854ad41fa0be3cb1",
  "sway_git_revision": "f1226936788f95418ef8a191f49731d2b3e3690d"
}
