{
  "phases": {
    "bytecode_size": 28,
    "metrics": [
      {
        "phase": "parse_cst",
        "elapsed": 0.005675163,
        "memory_usage": 1350123520
      },
      {
        "phase": "parse_ast",
        "elapsed": 0.208965934,
        "memory_usage": 1354264576
      },
      {
        "phase": "compile_to_ast",
        "elapsed": 0.215128802,
        "memory_usage": 1354264576
      },
      {
        "phase": "compile_ast_to_asm",
        "elapsed": 0.01073852,
        "memory_usage": 1354264576
      },
      {
        "phase": "generate_json_abi",
        "elapsed": 4e-07,
        "memory_usage": 1354264576
      },
      {
        "phase": "compile_asm_to_bytecode",
        "elapsed": 2.6e-05,
        "memory_usage": 1354264576
      }
    ]
  },
  "elapsed": "7.00",
  "cpu_usage": "99%",
  "memory": "454640KB",
  "build_type": "debug",
  "sway_apps_revision": "eb0aeb399be58cc43be3cc4ef490cb53c9ed65c8",
  "sway_libs_revision": "c6ed898128cc516fab72d924854ad41fa0be3cb1",
  "sway_git_revision": "2c6d410151b04f95be937faf5100ef98daf50a87"
}
