{
  "phases": {
    "bytecode_size": 28,
    "metrics": [
      {
        "phase": "compile_to_ast",
        "elapsed": 2.917646451,
        "memory_usage": 1658454016
      },
      {
        "phase": "compile_ast_to_asm",
        "elapsed": 0.031241233,
        "memory_usage": 1658454016
      },
      {
        "phase": "generate_json_abi",
        "elapsed": 9e-07,
        "memory_usage": 1658454016
      },
      {
        "phase": "compile_asm_to_bytecode",
        "elapsed": 2.6799e-05,
        "memory_usage": 1658454016
      }
    ],
    "reused_modules": 0
  },
  "elapsed": "14.54",
  "cpu_usage": "99%",
  "memory": "723500KB",
  "build_type": "debug",
  "sway_apps_revision": "718316e8092a4e326c790774c4c59b0d48736927",
  "sway_libs_revision": "c6ed898128cc516fab72d924854ad41fa0be3cb1",
  "sway_git_revision": "d37f706af75b41528073860c43bd1afb7041b69a"
}
