{
  "phases": {
    "bytecode_size": 28,
    "metrics": [
      {
        "phase": "compile_to_ast",
        "elapsed": 1.626534624,
        "memory_usage": 1677516800
      },
      {
        "phase": "compile_ast_to_asm",
        "elapsed": 0.018604767,
        "memory_usage": 1677516800
      },
      {
        "phase": "generate_json_abi",
        "elapsed": 5.31e-07,
        "memory_usage": 1677516800
      },
      {
        "phase": "compile_asm_to_bytecode",
        "elapsed": 2.1369e-05,
        "memory_usage": 1677516800
      }
    ],
    "reused_modules": 0
  },
  "elapsed": "9.74",
  "cpu_usage": "100%",
  "memory": "591700KB",
  "build_type": "debug",
  "sway_apps_revision": "72e8c1c3ee37d7ff07377e3738037388e052428f",
  "sway_libs_revision": "c6ed898128cc516fab72d924854ad41fa0be3cb1",
  "sway_git_revision": "ea0624bb85e0927fab3465863ed1bf28413d689e"
}
