{
  "phases": {
    "bytecode_size": 28,
    "metrics": [
      {
        "phase": "compile_to_ast",
        "elapsed": 1.08812957,
        "memory_usage": 1815191552
      },
      {
        "phase": "compile_ast_to_asm",
        "elapsed": 0.018061325,
        "memory_usage": 1815191552
      },
      {
        "phase": "generate_json_abi",
        "elapsed": 4.91e-07,
        "memory_usage": 1815191552
      },
      {
        "phase": "compile_asm_to_bytecode",
        "elapsed": 2.0518e-05,
        "memory_usage": 1815191552
      }
    ],
    "reused_modules": 0
  },
  "elapsed": "8.34",
  "cpu_usage": "100%",
  "memory": "691104KB",
  "build_type": "debug",
  "sway_apps_revision": "354bac23f11db6b2f89df53b46a8afe43c31911d",
  "sway_libs_revision": "c6ed898128cc516fab72d924854ad41fa0be3cb1",
  "sway_git_revision": "d3533713caf54dd06c5ef7ba896b8d2f6dd389af"
}
