{
  "phases": {
    "bytecode_size": 28,
    "metrics": [
      {
        "phase": "parse_cst",
        "elapsed": 0.007349062,
        "memory_usage": 1356402688
      },
      {
        "phase": "parse_ast",
        "elapsed": 0.147523545,
        "memory_usage": 1356402688
      },
      {
        "phase": "compile_to_ast",
        "elapsed": 0.155323405,
        "memory_usage": 1356402688
      },
      {
        "phase": "compile_ast_to_asm",
        "elapsed": 0.006405467,
        "memory_usage": 1356402688
      },
      {
        "phase": "generate_json_abi",
        "elapsed": 4e-07,
        "memory_usage": 1356402688
      },
      {
        "phase": "compile_asm_to_bytecode",
        "elapsed": 2.6499e-05,
        "memory_usage": 1356402688
      }
    ]
  },
  "elapsed": "6.82",
  "cpu_usage": "99%",
  "memory": "455676KB",
  "build_type": "debug",
  "sway_apps_revision": "031f5baf5ab7cf12258c91b73ce77c6610426247",
  "sway_libs_revision": "c6ed898128cc516fab72d924854ad41fa0be3cb1",
  "sway_git_revision": "99f4a800161d8aa6cd26552774bb6512c7b068bc"
}
