{
  "phases": {
    "bytecode_size": 28,
    "metrics": [
      {
        "phase": "compile_to_ast",
        "elapsed": 0.275616925,
        "memory_usage": 1555382272
      },
      {
        "phase": "compile_ast_to_asm",
        "elapsed": 0.011306556,
        "memory_usage": 1555382272
      },
      {
        "phase": "generate_json_abi",
        "elapsed": 6e-07,
        "memory_usage": 1555382272
      },
      {
        "phase": "compile_asm_to_bytecode",
        "elapsed": 2.43e-05,
        "memory_usage": 1555382272
      }
    ],
    "reused_modules": 0
  },
  "elapsed": "10.82",
  "cpu_usage": "99%",
  "memory": "628960KB",
  "build_type": "debug",
  "sway_apps_revision": "718316e8092a4e326c790774c4c59b0d48736927",
  "sway_libs_revision": "c6ed898128cc516fab72d924854ad41fa0be3cb1",
  "sway_git_revision": "67c431a1284950e2ed470b60605bb89e99da459d"
}
