{
  "phases": {
    "bytecode_size": 28,
    "metrics": [
      {
        "phase": "parse_cst",
        "elapsed": 0.005522886,
        "memory_usage": 1180778496
      },
      {
        "phase": "parse_ast",
        "elapsed": 0.254183557,
        "memory_usage": 1180778496
      },
      {
        "phase": "compile_to_ast",
        "elapsed": 0.260463755,
        "memory_usage": 1180778496
      },
      {
        "phase": "compile_ast_to_asm",
        "elapsed": 0.010983171,
        "memory_usage": 1180778496
      },
      {
        "phase": "generate_json_abi",
        "elapsed": 5e-07,
        "memory_usage": 1180778496
      },
      {
        "phase": "compile_asm_to_bytecode",
        "elapsed": 2.6e-05,
        "memory_usage": 1180778496
      }
    ]
  },
  "elapsed": "9.92",
  "cpu_usage": "99%",
  "memory": "612128KB",
  "build_type": "debug",
  "sway_apps_revision": "718316e8092a4e326c790774c4c59b0d48736927",
  "sway_libs_revision": "c6ed898128cc516fab72d924854ad41fa0be3cb1",
  "sway_git_revision": "bca210e41cc39395619ed48bb8cc8805a4c4f54e"
}
